logrus/__init__.py
logrus/_core.py
logrus/py.typed
logrus/pytest_plugin.py
python_logrus-0.1.0.dist-info/METADATA
python_logrus-0.1.0.dist-info/WHEEL
python_logrus-0.1.0.dist-info/top_level.txt
python_logrus-0.1.0.dist-info/RECORD
