Metadata-Version: 2.1
Name: python-logrus
Version: 0.1.0
Summary: Better logging made easy with support for structlog and the standard logging module.
Home-page: https://github.com/bbugyi200/logrus
Author: Bryan M Bugyi
Author-email: bryanbugyi34@gmail.com
License: MIT license
Platform: UNKNOWN
Classifier: Development Status :: 3 - Alpha
Classifier: Intended Audience :: Developers
Classifier: License :: OSI Approved :: MIT License
Classifier: Natural Language :: English
Classifier: Programming Language :: Python :: 3
Classifier: Programming Language :: Python :: 3.8
Classifier: Programming Language :: Python :: 3.9
Classifier: Programming Language :: Python :: 3.10
Requires-Python: >=3.8
Requires-Dist: bugyi.lib (~=0.11.0)
Requires-Dist: colorama (~=0.4.4)
Requires-Dist: structlog
